odoo/addons/base_user_role_menu/README.rst
odoo/addons/base_user_role_menu/__init__.py
odoo/addons/base_user_role_menu/__manifest__.py
odoo/addons/base_user_role_menu/data/ir_actions_server_data.xml
odoo/addons/base_user_role_menu/models/__init__.py
odoo/addons/base_user_role_menu/models/ir_ui_menu.py
odoo/addons/base_user_role_menu/static/description/icon.png
odoo/addons/base_user_role_menu/views/ir_ui_menu_views.xml
odoo14_addon_base_user_role_menu-14.0.1.0.1.dist-info/METADATA
odoo14_addon_base_user_role_menu-14.0.1.0.1.dist-info/WHEEL
odoo14_addon_base_user_role_menu-14.0.1.0.1.dist-info/top_level.txt
odoo14_addon_base_user_role_menu-14.0.1.0.1.dist-info/RECORD
